uart_devices/__init__.py
uart_devices/main.py
uart_devices/py.typed
uart_devices-0.0.1.dist-info/LICENSE
uart_devices-0.0.1.dist-info/METADATA
uart_devices-0.0.1.dist-info/WHEEL
uart_devices-0.0.1.dist-info/RECORD
