Metadata-Version: 2.1
Name: uart-devices
Version: 0.0.1
Summary: UART Devices for Linux
Home-page: https://github.com/bdraco/uart-devices
License: MIT
Author: J. Nick Koston
Author-email: nick@koston.org
Requires-Python: >=3.8,<4.0
Classifier: Development Status :: 2 - Pre-Alpha
Classifier: Intended Audience :: Developers
Classifier: License :: OSI Approved :: MIT License
Classifier: Natural Language :: English
Classifier: Operating System :: OS Independent
Classifier: Programming Language :: Python :: 3
Classifier: Programming Language :: Python :: 3.8
Classifier: Programming Language :: Python :: 3.9
Classifier: Programming Language :: Python :: 3.10
Classifier: Programming Language :: Python :: 3.11
Classifier: Programming Language :: Python :: 3.12
Classifier: Topic :: Software Development :: Libraries
Project-URL: Bug Tracker, https://github.com/bdraco/uart-devices/issues
Project-URL: Changelog, https://github.com/bdraco/uart-devices/blob/main/CHANGELOG.md
Project-URL: Documentation, https://uart-devices.readthedocs.io
Project-URL: Repository, https://github.com/bdraco/uart-devices
